svgoutline/__init__.py
svgoutline/outline_painter.py
svgoutline/svg_to_outlines.py
svgoutline/svg_utils.py
svgoutline/version.py
svgoutline-0.2.2.dist-info/LICENSE
svgoutline-0.2.2.dist-info/METADATA
svgoutline-0.2.2.dist-info/WHEEL
svgoutline-0.2.2.dist-info/top_level.txt
svgoutline-0.2.2.dist-info/RECORD
