Metadata-Version: 2.1
Name: svgoutline
Version: 0.2.2
Summary: Convert SVG files (including text) into simple lines and curves for plotters.
Home-page: https://github.com/mossblaser/svgoutline
Author: Jonathan Heathcote
License: LGPLv3
Keywords: svg outline plotter cutter
Classifier: Development Status :: 3 - Alpha
Classifier: Intended Audience :: Developers
Classifier: License :: OSI Approved :: GNU Lesser General Public License v3 (LGPLv3)
Classifier: Operating System :: POSIX :: Linux
Classifier: Operating System :: Microsoft :: Windows
Classifier: Operating System :: MacOS
Classifier: Programming Language :: Python :: 2
Classifier: Programming Language :: Python :: 2.7
Classifier: Programming Language :: Python :: 3
Classifier: Programming Language :: Python :: 3.5
License-File: LICENSE
Requires-Dist: PySide6 >=6.0.0
